jp_proxy_widget/__init__.py
jp_proxy_widget/_version.py
jp_proxy_widget/downloader.py
jp_proxy_widget/hex_codec.py
jp_proxy_widget/js_context.py
jp_proxy_widget/notebook_test_helpers.py
jp_proxy_widget/proxy_widget.py
jp_proxy_widget/uploader.py
jp_proxy_widget/watcher.py
jp_proxy_widget/js/FileSaver.js
jp_proxy_widget/js/README.md
jp_proxy_widget/js/require.js
jp_proxy_widget/js/simple.css
jp_proxy_widget/js/simple.js
jp_proxy_widget/js/simple_define.js
jp_proxy_widget/js/simple_upload_button.js
jp_proxy_widget/js/jquery-ui-1.12.1/AUTHORS.txt
jp_proxy_widget/js/jquery-ui-1.12.1/LICENSE.txt
jp_proxy_widget/js/jquery-ui-1.12.1/index.html
jp_proxy_widget/js/jquery-ui-1.12.1/jquery-ui.css
jp_proxy_widget/js/jquery-ui-1.12.1/jquery-ui.js
jp_proxy_widget/js/jquery-ui-1.12.1/jquery-ui.min.css
jp_proxy_widget/js/jquery-ui-1.12.1/jquery-ui.min.js
jp_proxy_widget/js/jquery-ui-1.12.1/jquery-ui.structure.css
jp_proxy_widget/js/jquery-ui-1.12.1/jquery-ui.structure.min.css
jp_proxy_widget/js/jquery-ui-1.12.1/jquery-ui.theme.css
jp_proxy_widget/js/jquery-ui-1.12.1/jquery-ui.theme.min.css
jp_proxy_widget/js/jquery-ui-1.12.1/package.json
jp_proxy_widget/js/jquery-ui-1.12.1/external/jquery/jquery.js
jp_proxy_widget/js/jquery-ui-1.12.1/images/ui-icons_444444_256x240.png
jp_proxy_widget/js/jquery-ui-1.12.1/images/ui-icons_555555_256x240.png
jp_proxy_widget/js/jquery-ui-1.12.1/images/ui-icons_777620_256x240.png
jp_proxy_widget/js/jquery-ui-1.12.1/images/ui-icons_777777_256x240.png
jp_proxy_widget/js/jquery-ui-1.12.1/images/ui-icons_cc0000_256x240.png
jp_proxy_widget/js/jquery-ui-1.12.1/images/ui-icons_ffffff_256x240.png
jp_proxy_widget/static/extension.js
jp_proxy_widget/static/index.js
jp_proxy_widget/static/index.js.map
jp_proxy_widget-1.0.10.data/data/etc/jupyter/nbconfig/notebook.d/jp_proxy_widget.json
jp_proxy_widget-1.0.10.data/data/share/jupyter/nbextensions/jp_proxy_widget/extension.js
jp_proxy_widget-1.0.10.data/data/share/jupyter/nbextensions/jp_proxy_widget/index.js
jp_proxy_widget-1.0.10.dist-info/LICENSE
jp_proxy_widget-1.0.10.dist-info/METADATA
jp_proxy_widget-1.0.10.dist-info/WHEEL
jp_proxy_widget-1.0.10.dist-info/top_level.txt
jp_proxy_widget-1.0.10.dist-info/RECORD
