Metadata-Version: 2.1
Name: jp-proxy-widget
Version: 1.0.10
Summary: Generic Jupyter/IPython widget implementation that will support many types of javascript libraries and interactions.
Home-page: https://github.com/AaronWatters/jp_proxy_widget
Author: Aaron Watters
Author-email: awatters@flatironinstitute.org
License: UNKNOWN
Keywords: ipython,jupyter,widgets
Platform: UNKNOWN
Classifier: Development Status :: 4 - Beta
Classifier: Framework :: IPython
Classifier: Intended Audience :: Developers
Classifier: Intended Audience :: Science/Research
Classifier: Topic :: Multimedia :: Graphics
Classifier: Programming Language :: Python :: 2
Classifier: Programming Language :: Python :: 2.7
Classifier: Programming Language :: Python :: 3
Classifier: Programming Language :: Python :: 3.3
Classifier: Programming Language :: Python :: 3.4
Classifier: Programming Language :: Python :: 3.5
Requires-Dist: ipywidgets (>=7.0.0)
Requires-Dist: requests
Requires-Dist: numpy
Requires-Dist: jupyter-ui-poll
